LICENSE
MANIFEST.in
README.rst
setup.py
evo_pyzipper.egg-info/PKG-INFO
evo_pyzipper.egg-info/SOURCES.txt
evo_pyzipper.egg-info/dependency_links.txt
evo_pyzipper.egg-info/requires.txt
evo_pyzipper.egg-info/top_level.txt
pyzipper/__init__.py
pyzipper/__version__.py
pyzipper/zipfile.py
pyzipper/zipfile_aes.py
test/__init__.py
test/badsyntax_3131.py
test/badsyntax_future10.py
test/badsyntax_future3.py
test/badsyntax_future4.py
test/badsyntax_future5.py
test/badsyntax_future6.py
test/badsyntax_future7.py
test/badsyntax_future8.py
test/badsyntax_future9.py
test/badsyntax_pep3120.py
test/test_support.py
test/test_zipfile.py
test/test_zipfile2.py
test/test_zipfile64.py
test/test_zipfile_aes.py
test/support/__init__.py
test/support/script_helper.py
test/support/testresult.py