Metadata-Version: 1.2
Name: evo-pyzipper
Version: 0.3.2
Summary: AES encryption for zipfile. Including Callback.
Home-page: https://github.com/evotodi/pyzipper
Author: Justin Davis
Author-email: evotodi@gmail.com
License: MIT
Keywords: zip aes encrypt decrypt
Platform: UNKNOWN
Classifier: Development Status :: 4 - Beta
Classifier: Topic :: System :: Archiving :: Compression
Classifier: Intended Audience :: Developers
Classifier: Operating System :: MacOS :: MacOS X
Classifier: Operating System :: Microsoft :: Windows
Classifier: Operating System :: POSIX :: Linux
Classifier: Operating System :: POSIX
Classifier: License :: OSI Approved :: MIT License
Classifier: Operating System :: OS Independent
Classifier: Programming Language :: Python
Classifier: Programming Language :: Python :: 3
Classifier: Programming Language :: Python :: 3.4
Classifier: Programming Language :: Python :: 3.5
Classifier: Programming Language :: Python :: 3.6
Classifier: Programming Language :: Python :: 3.7
Requires-Python: >=3.4
